{"gastronomica":"Winter 2020","economist":"2021-01-16","podmass":"https://aux.avclub.com/for-inauguration-week-here-are-the-best-podcasts-about-1846056736","needleDrop":"Lana Del Rey, DaBaby, Juice WRLD, Ameer Vann | Weekly Track Roundup: 1/18/21","allSongs":"New Music Friday: Jan. 15","altLatino":"Tiny Desk Artist Profile: Sofia Rei","crossword":"https://www.newyorker.com/puzzles-and-games-dept/crossword/2021/01/20","cryptic":"https://www.newyorker.com/magazine/1999/02/22","atlantic":" january/february 2021 "}